Workbook

Sheet Read me
A1: How live AI during play can pay for itself: the model
A2: Runtime-AI business model, LEDGER. Built 2026-09-24 for production/research/runtime-ai-business. Nothing here is a decision.
A4: HOW TO USE IT
A5: 1. Change only the BLUE numbers on the Inputs sheet. Yellow ones are the key assumptions; the cost per hour is the one to replace with our measured figure.
A6: 2. The Models sheet shows, for each business model, what one typical player, one heavy player and the average player earn or lose us.
A7: 3. The Grid sheet shows the plain one-time purchase across a range of costs per hour and hours played, so you can see where it breaks.
A8: 4. The Prices sheet holds the dated price history and the decline assumption that turns today's cost into the cost at launch.
A10: COLOURS
A11: Blue text: an input you can change. Black: a formula. Green: a figure pulled from another sheet. Yellow fill: a key assumption.
A13: WHAT IT LEAVES OUT, ON PURPOSE
A14: Development cost, marketing, refunds, regional pricing, tax and currency. It answers one question: does each player pay for the talking they do.
A15: All money is in US dollars, because model prices are quoted in dollars.

Sheet Inputs
A1: Inputs: change the blue numbers
A2: Every result in this workbook is computed from this sheet. Units are in the label; notes say where each default came from.
A4: Input | B4: Value | C4: Unit | D4: Where the default comes from
A6: The talking: what an hour of play costs
A7: Cost per hour of live talk, all of it on the paid model, at today's prices | B7: 0.14 | C7: $ per player-hour | D7: PLACEHOLDER until the slice measures it. Topic 19 (llm-inference-economics) estimated $0.36/h for all-cheap-tier characters at 20 conversations an hour, and about $0.14/h with prompt caching on. Replace with the measured figure.
A8: Share of today's live talk that is written ahead instead (barks, remarks, stock replies) | B8: 0 | C8: share | D8: A design choice. 0 means every line is generated live, as measured. Written-ahead lines cost nothing per hour.
A9: Share of the per-hour cost that is writing the spoken line (the rest is picking the action) | B9: 0.7 | C9: share | D9: DERIVED: a spoken line is about 1,950 tokens in and 60 out ($0.0023 uncached at Haiku 4.5 prices), an action-pick about 830 in and 48 out (about $0.0011). So writing the line is roughly 70% of the cost. Replace from the slice's own split.
A10: Action-picking runs on the player's card (1 yes, 0 no) | B10: 0 | C10: switch | D10: Measured 24 Sep: a free model on the RX 6700 nearly matches the paid router with worked examples, but obeys more typed orders and takes 1.4 s a line.
A11: Line-writing runs on the player's card (1 yes, 0 no) | B11: 0 | C11: switch | D11: Not yet tested; queued on the checklist as L01, waiting on the slice's card measurement.
A12: Price fall per year for the same capability | B12: 0 | C12: share per year | D12: Default 0: budget at today's price. Anthropic's small model has held or raised its price for three years (Haiku 3 $0.25/$1.25, Haiku 3.5 $0.80/$4, Haiku 4.5 $1/$5). A fixed capability falls 5-13x a year elsewhere (Epoch AI 2025-2026, a16z 2024), but only if the dialogue can move to a cheaper model. Central case if it can: about 75% in the first year.
A13: Years from today until launch | B13: 1.5 | C13: years | D13: A plan figure, not a fact.
A14: Our relay server, per player-hour (keeps the key off players' machines, enforces limits) | B14: 0.0005 | C14: $ per player-hour | D14: DERIVED from the plumbing research: Cloudflare Workers about $5-7 a month at 1,000-20,000 monthly players at 10 hours each, i.e. well under $0.0001 an hour. Set higher here to cover logging and a spare. Negligible either way.
A15: Cost per hour of the paid model at launch, before design choices | B15: =Inputs!$B$7*(1-Inputs!$B$12)^Inputs!$B$13 | C15: $ per player-hour | D15: Today's cost carried forward at the price-fall rate.
A16: Cost per hour at launch, after the design choices above | B16: =Inputs!$B$15*(1-Inputs!$B$8)*(1-Inputs!$B$9*Inputs!$B$11-(1-Inputs!$B$9)*Inputs!$B$10)+Inputs!$B$14*IF(Inputs!$B$10*Inputs!$B$11=1,0,1) | C16: $ per player-hour | D16: What one hour of a cloud player's talk costs us at launch, relay included.
A18: The players
A19: Hours a typical player plays in total | B19: 15 | C19: hours | D19: ASSUMED, a median player. GameDiscoverCo's Steam data (2025): median playtime 6.6-7.5 hours in comparable genres; about 36% of owners finish a single-player game.
A20: Hours a heavy player plays in total | B20: 120 | C20: hours | D20: ASSUMED. GameDiscoverCo: average playtime runs 3-4 times the median, so a long tail of heavy players. Suck Up! capped its included AI at about 40-50 hours; AI Dungeon rationed its heaviest 7%.
A21: Share of players who are heavy | B21: 0.2 | C21: share | D21: The top slice of players by hours. They drive most of the cost in any model where we absorb it.
A22: Share of players whose own PC runs all the talk locally | B22: 0.5 | C22: share | D22: Only matters in the hybrid model. Depends on what model fits beside the game, and on the card memory the slice will measure.
A23: Hours played per month while playing | B23: 15 | C23: hours per month | D23: Used to count subscription months.
A25: The price and the store
A26: Price of the game | B26: 24.99 | C26: $ | D26: ASSUMED, an indie price. Comparables: Suck Up! $15.99, Whispers from the Star $9.99, Disco Elysium launch $39.99.
A27: Store's share of every sale and purchase | B27: 0.3 | C27: share | D27: Steam's standard share on the first $10M of revenue. Steam also takes its cut of in-game purchases, which must go through the Steam Wallet.
A28: Hours of live talk included in the price (capped and hybrid models) | B28: 40 | C28: hours | D28: After the cap, talk falls back to written lines and the in-character brush-off already ruled for a dropped connection.
A29: Price the player pays per extra hour of talk (credits model) | B29: 0.5 | C29: $ per hour | D29: ASSUMED. Comparables: AI Dungeon about $9.99 for 1,200 credits; Master of Dungeon from EUR 3.09 for 200 actions; Tabled $4.99 refills.
A30: Share of players who buy credits once the included hours run out | B30: 0.2 | C30: share | D30: The rest carry on with written lines.
A31: Subscription price per month (subscription model) | B31: 4.99 | C31: $ per month | D31: ASSUMED. Valve: recurring billing is 'not a fully supported feature' and 'customer appetite is limited'. Comparables are standalone AI apps at $10-15 (NovelAI, AI Dungeon, Character.AI).
A32: Share of players who subscribe once the included hours run out | B32: 0.1 | C32: share | D32: The rest carry on with written lines.
A33: Sales lost because the player must bring their own key | B33: 0.5 | C33: share of sales | D33: ASSUMED; no published take-up figure exists. Games that require a key (1001 Nights) are niche; most move to a free default (AI Roguelite, Player2-backed mods).
A34: Share of buyers who actually set up a key | B34: 0.2 | C34: share | D34: The rest get written lines only.

Sheet Models
A1: What each business model earns or loses per player
A2: Net = what the player pays us after the store's share, minus what their talking costs us. Positive means the player pays for their own talk.
A4: Business model | B4: How it works | C4: Typical player: we receive | D4: Typical: talk costs us | E4: Typical: net | F4: Heavy player: we receive | G4: Heavy: talk costs us | H4: Heavy: net | I4: Average player: net | J4: Hours at which a player stops paying for themselves
A5: One-time purchase, cost absorbed | B5: The player buys the game once; we pay for every hour of talk, forever. | C5: =Inputs!$B$26*(1-Inputs!$B$27) | D5: =Inputs!$B$19*Inputs!$B$16 | E5: =C5-D5 | F5: =Inputs!$B$26*(1-Inputs!$B$27) | G5: =Inputs!$B$20*Inputs!$B$16 | H5: =F5-G5 | I5: =(1-Inputs!$B$21)*E5+Inputs!$B$21*H5 | J5: =IFERROR(Inputs!$B$26*(1-Inputs!$B$27)/Inputs!$B$16,"never")
A6: One-time purchase with included hours | B6: The price includes a set number of hours of live talk; after that the street carries on with written lines. | C6: =Inputs!$B$26*(1-Inputs!$B$27) | D6: =MIN(Inputs!$B$19,Inputs!$B$28)*Inputs!$B$16 | E6: =C6-D6 | F6: =Inputs!$B$26*(1-Inputs!$B$27) | G6: =MIN(Inputs!$B$20,Inputs!$B$28)*Inputs!$B$16 | H6: =F6-G6 | I6: =(1-Inputs!$B$21)*E6+Inputs!$B$21*H6 | J6: =IF(Inputs!$B$28*Inputs!$B$16<=Inputs!$B$26*(1-Inputs!$B$27),"never",IFERROR(Inputs!$B$26*(1-Inputs!$B$27)/Inputs!$B$16,"never"))
A7: Included hours, then credits | B7: As above, and players who want more buy hours of talk. | C7: =Inputs!$B$26*(1-Inputs!$B$27)+Inputs!$B$30*MAX(0,Inputs!$B$19-Inputs!$B$28)*Inputs!$B$29*(1-Inputs!$B$27) | D7: =(MIN(Inputs!$B$19,Inputs!$B$28)+Inputs!$B$30*MAX(0,Inputs!$B$19-Inputs!$B$28))*Inputs!$B$16 | E7: =C7-D7 | F7: =Inputs!$B$26*(1-Inputs!$B$27)+Inputs!$B$30*MAX(0,Inputs!$B$20-Inputs!$B$28)*Inputs!$B$29*(1-Inputs!$B$27) | G7: =(MIN(Inputs!$B$20,Inputs!$B$28)+Inputs!$B$30*MAX(0,Inputs!$B$20-Inputs!$B$28))*Inputs!$B$16 | H7: =F7-G7 | I7: =(1-Inputs!$B$21)*E7+Inputs!$B$21*H7 | J7: =IF(Inputs!$B$29*(1-Inputs!$B$27)>=Inputs!$B$16,"never","see note")
A8: Included hours, then a subscription | B8: As above, and players who want more subscribe by the month. | C8: =Inputs!$B$26*(1-Inputs!$B$27)+Inputs!$B$32*ROUNDUP(MAX(0,Inputs!$B$19-Inputs!$B$28)/Inputs!$B$23,0)*Inputs!$B$31*(1-Inputs!$B$27) | D8: =(MIN(Inputs!$B$19,Inputs!$B$28)+Inputs!$B$32*MAX(0,Inputs!$B$19-Inputs!$B$28))*Inputs!$B$16 | E8: =C8-D8 | F8: =Inputs!$B$26*(1-Inputs!$B$27)+Inputs!$B$32*ROUNDUP(MAX(0,Inputs!$B$20-Inputs!$B$28)/Inputs!$B$23,0)*Inputs!$B$31*(1-Inputs!$B$27) | G8: =(MIN(Inputs!$B$20,Inputs!$B$28)+Inputs!$B$32*MAX(0,Inputs!$B$20-Inputs!$B$28))*Inputs!$B$16 | H8: =F8-G8 | I8: =(1-Inputs!$B$21)*E8+Inputs!$B$21*H8 | J8: =IF(Inputs!$B$31*(1-Inputs!$B$27)>=Inputs!$B$23*Inputs!$B$16,"never","see note")
A9: Player brings their own key | B9: The player pays the model provider directly; we pay nothing per hour. Players without a key get written lines only. | C9: =Inputs!$B$26*(1-Inputs!$B$27)*(1-Inputs!$B$33) | D9: =0 | E9: =C9-D9 | F9: =Inputs!$B$26*(1-Inputs!$B$27)*(1-Inputs!$B$33) | G9: =0 | H9: =F9-G9 | I9: =(1-Inputs!$B$21)*E9+Inputs!$B$21*H9 | J9: ="never"
A10: Everything runs on the player's PC | B10: No per-hour cost at all, but only players whose PC can run it get live talk. | C10: =Inputs!$B$26*(1-Inputs!$B$27) | D10: =0 | E10: =C10-D10 | F10: =Inputs!$B$26*(1-Inputs!$B$27) | G10: =0 | H10: =F10-G10 | I10: =(1-Inputs!$B$21)*E10+Inputs!$B$21*H10 | J10: ="never"
A11: Hybrid: local where the PC can, included hours on our servers where it cannot | B11: Players with a capable PC run it locally; the rest get the included hours from us, then written lines. | C11: =Inputs!$B$26*(1-Inputs!$B$27) | D11: =(1-Inputs!$B$22)*MIN(Inputs!$B$19,Inputs!$B$28)*Inputs!$B$16 | E11: =C11-D11 | F11: =Inputs!$B$26*(1-Inputs!$B$27) | G11: =(1-Inputs!$B$22)*MIN(Inputs!$B$20,Inputs!$B$28)*Inputs!$B$16 | H11: =F11-G11 | I11: =(1-Inputs!$B$21)*E11+Inputs!$B$21*H11 | J11: =IF(Inputs!$B$28*Inputs!$B$16<=Inputs!$B$26*(1-Inputs!$B$27),"never",IFERROR(Inputs!$B$26*(1-Inputs!$B$27)/Inputs!$B$16,"never"))
A13: Notes
A14: Hours at which a player stops paying for themselves: the point where their talk has cost us everything they paid. 'never' means they pay for themselves however long they play.
A15: Credits and subscription: 'never' when every extra hour sold earns more than it costs; 'see note' when it does not, in which case the heavy player's net column shows how much.
A16: Bring your own key: we pay nothing per hour, and lose the buyers who will not set up a key (input 'Sales lost').
A17: Everything local: no running cost, but the talk is only as good as a model that fits beside the game on the player's card. The local-models research (24 Sep) measured the action-picking half only.
A18: The cost per hour on every row is the launch figure from the Inputs sheet, after the design choices (written-ahead share, local action-picking, local line-writing).
A20: Key figures from the Inputs sheet
A21: Cost per hour today (input) | C21: =Inputs!$B$7
A22: Cost per hour at launch, after design choices | C22: =Inputs!$B$16
A23: What we receive per sale after the store's share | C23: =Inputs!$B$26*(1-Inputs!$B$27)
A24: Hours of talk one sale pays for at launch | C24: =IFERROR(Inputs!$B$26*(1-Inputs!$B$27)/Inputs!$B$16,"unlimited")

Sheet Grid
A1: One-time purchase, cost absorbed: net per player
A2: Rows: cost per hour at launch. Columns: total hours a player plays. Each cell: price after the store's share, minus hours x cost. Negative (in brackets) means that player costs us money.
A4: Cost per hour at launch | B4: 5 | C4: 10 | D4: 20 | E4: 40 | F4: 60 | G4: 100 | H4: 200
A5: 0.01 | B5: =Inputs!$B$26*(1-Inputs!$B$27)-$A5*B$4 | C5: =Inputs!$B$26*(1-Inputs!$B$27)-$A5*C$4 | D5: =Inputs!$B$26*(1-Inputs!$B$27)-$A5*D$4 | E5: =Inputs!$B$26*(1-Inputs!$B$27)-$A5*E$4 | F5: =Inputs!$B$26*(1-Inputs!$B$27)-$A5*F$4 | G5: =Inputs!$B$26*(1-Inputs!$B$27)-$A5*G$4 | H5: =Inputs!$B$26*(1-Inputs!$B$27)-$A5*H$4
A6: 0.02 | B6: =Inputs!$B$26*(1-Inputs!$B$27)-$A6*B$4 | C6: =Inputs!$B$26*(1-Inputs!$B$27)-$A6*C$4 | D6: =Inputs!$B$26*(1-Inputs!$B$27)-$A6*D$4 | E6: =Inputs!$B$26*(1-Inputs!$B$27)-$A6*E$4 | F6: =Inputs!$B$26*(1-Inputs!$B$27)-$A6*F$4 | G6: =Inputs!$B$26*(1-Inputs!$B$27)-$A6*G$4 | H6: =Inputs!$B$26*(1-Inputs!$B$27)-$A6*H$4
A7: 0.05 | B7: =Inputs!$B$26*(1-Inputs!$B$27)-$A7*B$4 | C7: =Inputs!$B$26*(1-Inputs!$B$27)-$A7*C$4 | D7: =Inputs!$B$26*(1-Inputs!$B$27)-$A7*D$4 | E7: =Inputs!$B$26*(1-Inputs!$B$27)-$A7*E$4 | F7: =Inputs!$B$26*(1-Inputs!$B$27)-$A7*F$4 | G7: =Inputs!$B$26*(1-Inputs!$B$27)-$A7*G$4 | H7: =Inputs!$B$26*(1-Inputs!$B$27)-$A7*H$4
A8: 0.1 | B8: =Inputs!$B$26*(1-Inputs!$B$27)-$A8*B$4 | C8: =Inputs!$B$26*(1-Inputs!$B$27)-$A8*C$4 | D8: =Inputs!$B$26*(1-Inputs!$B$27)-$A8*D$4 | E8: =Inputs!$B$26*(1-Inputs!$B$27)-$A8*E$4 | F8: =Inputs!$B$26*(1-Inputs!$B$27)-$A8*F$4 | G8: =Inputs!$B$26*(1-Inputs!$B$27)-$A8*G$4 | H8: =Inputs!$B$26*(1-Inputs!$B$27)-$A8*H$4
A9: 0.15 | B9: =Inputs!$B$26*(1-Inputs!$B$27)-$A9*B$4 | C9: =Inputs!$B$26*(1-Inputs!$B$27)-$A9*C$4 | D9: =Inputs!$B$26*(1-Inputs!$B$27)-$A9*D$4 | E9: =Inputs!$B$26*(1-Inputs!$B$27)-$A9*E$4 | F9: =Inputs!$B$26*(1-Inputs!$B$27)-$A9*F$4 | G9: =Inputs!$B$26*(1-Inputs!$B$27)-$A9*G$4 | H9: =Inputs!$B$26*(1-Inputs!$B$27)-$A9*H$4
A10: 0.25 | B10: =Inputs!$B$26*(1-Inputs!$B$27)-$A10*B$4 | C10: =Inputs!$B$26*(1-Inputs!$B$27)-$A10*C$4 | D10: =Inputs!$B$26*(1-Inputs!$B$27)-$A10*D$4 | E10: =Inputs!$B$26*(1-Inputs!$B$27)-$A10*E$4 | F10: =Inputs!$B$26*(1-Inputs!$B$27)-$A10*F$4 | G10: =Inputs!$B$26*(1-Inputs!$B$27)-$A10*G$4 | H10: =Inputs!$B$26*(1-Inputs!$B$27)-$A10*H$4
A11: 0.4 | B11: =Inputs!$B$26*(1-Inputs!$B$27)-$A11*B$4 | C11: =Inputs!$B$26*(1-Inputs!$B$27)-$A11*C$4 | D11: =Inputs!$B$26*(1-Inputs!$B$27)-$A11*D$4 | E11: =Inputs!$B$26*(1-Inputs!$B$27)-$A11*E$4 | F11: =Inputs!$B$26*(1-Inputs!$B$27)-$A11*F$4 | G11: =Inputs!$B$26*(1-Inputs!$B$27)-$A11*G$4 | H11: =Inputs!$B$26*(1-Inputs!$B$27)-$A11*H$4
A12: 0.6 | B12: =Inputs!$B$26*(1-Inputs!$B$27)-$A12*B$4 | C12: =Inputs!$B$26*(1-Inputs!$B$27)-$A12*C$4 | D12: =Inputs!$B$26*(1-Inputs!$B$27)-$A12*D$4 | E12: =Inputs!$B$26*(1-Inputs!$B$27)-$A12*E$4 | F12: =Inputs!$B$26*(1-Inputs!$B$27)-$A12*F$4 | G12: =Inputs!$B$26*(1-Inputs!$B$27)-$A12*G$4 | H12: =Inputs!$B$26*(1-Inputs!$B$27)-$A12*H$4
A13: 1 | B13: =Inputs!$B$26*(1-Inputs!$B$27)-$A13*B$4 | C13: =Inputs!$B$26*(1-Inputs!$B$27)-$A13*C$4 | D13: =Inputs!$B$26*(1-Inputs!$B$27)-$A13*D$4 | E13: =Inputs!$B$26*(1-Inputs!$B$27)-$A13*E$4 | F13: =Inputs!$B$26*(1-Inputs!$B$27)-$A13*F$4 | G13: =Inputs!$B$26*(1-Inputs!$B$27)-$A13*G$4 | H13: =Inputs!$B$26*(1-Inputs!$B$27)-$A13*H$4

Sheet Prices
A1: What a small-model call has cost, and what to assume
A2: Dated list prices per million tokens. Sources in DELIVERY.md. The derived rate below is a plain compound rate between two dated points.
A4: Model | B4: Price took effect | C4: Input $ per million tokens | D4: Output $ per million tokens | E4: Source (see DELIVERY.md)
A5: Claude Instant 1.2 (Anthropic) | B5: 2023-08 | C5: 1.63 | D5: 5.51 | E5: biz-prices: Anthropic pricing, via Wayback
A6: Claude 3 Haiku (Anthropic) | B6: 2024-03 | C6: 0.25 | D6: 1.25 | E6: Anthropic launch post
A7: Claude 3.5 Haiku (Anthropic) | B7: 2024-11 | C7: 1 | D7: 5 | E7: Anthropic; later $0.80/$4
A8: Claude Haiku 4.5 (Anthropic) | B8: 2025-10 | C8: 1 | D8: 5 | E8: Anthropic pricing page
A9: GPT-4o mini (OpenAI) | B9: 2024-07 | C9: 0.15 | D9: 0.6 | E9: OpenAI launch post
A10: GPT-6 Luna (OpenAI) | B10: 2026-09 | C10: 0.1 | D10: 0.5 | E10: OpenAI, 22 Sep 2026
A11: Cheapest model at Haiku 4.5's level, est. | B11: 2024-09 | C11: 2.75 | D11: 12.5 | E11: DERIVED in biz-prices (range $2.50-3 / $10-15)
A12: Cheapest model at Haiku 4.5's level, est. | B12: 2026-09 | C12: 0.2 | D12: 1.25 | E12: DERIVED in biz-prices (range $0.10-0.30 / $0.50-2); not tested on our dialogue
A14: Derived: the fall per year between two points you choose
A15: Earlier price ($ per million, blended) | C15: =(3*C11+D11)/4 | D15: Blended at 3 input : 1 output, cheapest at Haiku 4.5's level, Sep 2024
A16: Later price ($ per million, blended) | C16: =(3*C12+D12)/4 | D16: Same, Sep 2026
A17: Years between them | C17: 2
A18: Fall per year | C18: =IFERROR(1-(C16/C15)^(1/C17),0) | D18: Compare with the input on the Inputs sheet; the input is what the model uses.
